systemd_web.py
systemd_web-0.0.2.dist-info/METADATA
systemd_web-0.0.2.dist-info/WHEEL
systemd_web-0.0.2.dist-info/top_level.txt
systemd_web-0.0.2.dist-info/RECORD
