Metadata-Version: 2.4
Name: systemd-web
Version: 0.0.2
Summary: A super simple web control for start/stop/restart/status of systemd services
Requires-Python: >=3.9
Requires-Dist: flask>=3.1.0
Requires-Dist: gunicorn>=23.0.0
Requires-Dist: python-dotenv>=1.0.1
